MANIFEST.in
setup.py
VEP_Core.egg-info/PKG-INFO
VEP_Core.egg-info/SOURCES.txt
VEP_Core.egg-info/dependency_links.txt
VEP_Core.egg-info/entry_points.txt
VEP_Core.egg-info/not-zip-safe
VEP_Core.egg-info/requires.txt
VEP_Core.egg-info/top_level.txt
vep_core/__init__.py
vep_core/Apps/FilePathsApp.py
vep_core/Apps/JSONCorpusImporterApp.py
vep_core/Apps/ModelCleanser.py
vep_core/Apps/SaliencyTopicModelerApp.py
vep_core/Apps/__init__.py
vep_core/Apps/FormatterApps/CSVFormatterApp.py
vep_core/Apps/FormatterApps/HTMLFormatterTest.py
vep_core/Apps/FormatterApps/TopicModelCacheApp.py
vep_core/Apps/TaggerApps/DocuscopeTaggerApp.py
vep_core/Apps/TaggerApps/DocuscopeTaggerTests.py
vep_core/Apps/TaggerApps/SimpleRuleTaggerApp.py
vep_core/Apps/TaggerApps/SimpleTaggerTest.py
vep_core/Apps/TaggerApps/TaggerPerfTest.py
vep_core/Apps/TaggerApps/TopicModelTaggerApp.py
vep_core/Apps/TokenizerApps/TokenizerPerfTest.py
vep_core/Apps/TokenizerApps/TokenizerTestApp.py
vep_core/Data/Corpora/README.txt
vep_core/Data/Metadata/README.txt
vep_core/Data/Metadata/ShakespeareChunked_50/TopicModel/HTML.zip
vep_core/Data/Metadata/ShakespeareChunked_50/TopicModel/fullTheta.csv
vep_core/Data/Metadata/ShakespeareChunked_50/TopicModel/metadata.csv
vep_core/Data/Metadata/ShakespeareChunked_50/TopicModel/theta.csv
vep_core/Data/Metadata/ShakespeareChunked_50/TopicModel/topics_freq/topic_0.csv
vep_core/Data/Metadata/ShakespeareChunked_50/TopicModel/topics_freq/topic_1.csv
vep_core/Data/Metadata/ShakespeareChunked_50/TopicModel/topics_freq/topic_10.csv
vep_core/Data/Metadata/ShakespeareChunked_50/TopicModel/topics_freq/topic_11.csv
vep_core/Data/Metadata/ShakespeareChunked_50/TopicModel/topics_freq/topic_12.csv
vep_core/Data/Metadata/ShakespeareChunked_50/TopicModel/topics_freq/topic_13.csv
vep_core/Data/Metadata/ShakespeareChunked_50/TopicModel/topics_freq/topic_14.csv
vep_core/Data/Metadata/ShakespeareChunked_50/TopicModel/topics_freq/topic_15.csv
vep_core/Data/Metadata/ShakespeareChunked_50/TopicModel/topics_freq/topic_16.csv
vep_core/Data/Metadata/ShakespeareChunked_50/TopicModel/topics_freq/topic_17.csv
vep_core/Data/Metadata/ShakespeareChunked_50/TopicModel/topics_freq/topic_18.csv
