Metadata-Version: 1.0
Name: VEP-Core
Version: 1.0
Summary: VEP Core contains the Serendip corpus exploration tool.
Home-page: UNKNOWN
Author: Eric Alexander
Author-email: ealexand@cs.wisc.edu
License: BSD
Platform: UNKNOWN
